odoo/addons/account_asset_disposal/README.rst
odoo/addons/account_asset_disposal/__init__.py
odoo/addons/account_asset_disposal/__manifest__.py
odoo/addons/account_asset_disposal/i18n/account_asset_disposal.pot
odoo/addons/account_asset_disposal/i18n/de.po
odoo/addons/account_asset_disposal/i18n/es.po
odoo/addons/account_asset_disposal/i18n/hr.po
odoo/addons/account_asset_disposal/models/__init__.py
odoo/addons/account_asset_disposal/models/account_asset_asset.py
odoo/addons/account_asset_disposal/models/account_asset_category.py
odoo/addons/account_asset_disposal/readme/CONFIGURE.rst
odoo/addons/account_asset_disposal/readme/CONTRIBUTORS.rst
odoo/addons/account_asset_disposal/readme/DESCRIPTION.rst
odoo/addons/account_asset_disposal/readme/ROADMAP.rst
odoo/addons/account_asset_disposal/readme/USAGE.rst
odoo/addons/account_asset_disposal/static/description/icon.png
odoo/addons/account_asset_disposal/static/description/index.html
odoo/addons/account_asset_disposal/tests/__init__.py
odoo/addons/account_asset_disposal/tests/test_account_asset_disposal.py
odoo/addons/account_asset_disposal/views/account_asset_asset_views.xml
odoo/addons/account_asset_disposal/views/account_asset_category_views.xml
odoo/addons/account_asset_disposal/wizards/__init__.py
odoo/addons/account_asset_disposal/wizards/account_asset_disposal_wizard.py
odoo/addons/account_asset_disposal/wizards/account_asset_disposal_wizard_view.xml
odoo11_addon_account_asset_disposal-11.0.1.0.0.99.dev4.dist-info/METADATA
odoo11_addon_account_asset_disposal-11.0.1.0.0.99.dev4.dist-info/WHEEL
odoo11_addon_account_asset_disposal-11.0.1.0.0.99.dev4.dist-info/top_level.txt
odoo11_addon_account_asset_disposal-11.0.1.0.0.99.dev4.dist-info/RECORD
